NQvision/__init__.py
NQvision/core.py
NQvision/events.py
NQvision-0.1.2.dist-info/LICENCE
NQvision-0.1.2.dist-info/METADATA
NQvision-0.1.2.dist-info/WHEEL
NQvision-0.1.2.dist-info/top_level.txt
NQvision-0.1.2.dist-info/RECORD
