Metadata-Version: 2.1
Name: NQvision
Version: 0.1.2
Summary: A library to simplify the development of AI-driven object detection and monitoring solutions.
Home-page: https://neuronq.io
Author: Neuron Q
Author-email: debbichi.raki@neuronq.io
License: MIT
Keywords: computer vision,object detection,tracking,CUDA,enterprise
Classifier: Development Status :: 3 - Alpha
Classifier: Intended Audience :: Developers
Classifier: License :: OSI Approved :: MIT License
Classifier: Operating System :: OS Independent
Classifier: Programming Language :: Python :: 3
Classifier: Programming Language :: Python :: 3.7
Classifier: Programming Language :: Python :: 3.8
Classifier: Programming Language :: Python :: 3.9
Requires-Python: >=3.7
License-File: LICENCE
Requires-Dist: numpy
Requires-Dist: opencv-python
Requires-Dist: Pillow
Requires-Dist: deep-sort-realtime
Requires-Dist: torch
Requires-Dist: torchvision
Requires-Dist: vidgear
Requires-Dist: numba
